processamento_imagem/__init__.py
processamento_imagem/processing/__init__.py
processamento_imagem/processing/combination.py
processamento_imagem/processing/transformation.py
processamento_imagem/utils/__init__.py
processamento_imagem/utils/io.py
processamento_imagem/utils/plot.py
processamento_imagem_bz-0.0.1.dist-info/METADATA
processamento_imagem_bz-0.0.1.dist-info/WHEEL
processamento_imagem_bz-0.0.1.dist-info/top_level.txt
processamento_imagem_bz-0.0.1.dist-info/RECORD
