Metadata-Version: 2.1
Name: processamento-imagem-bz
Version: 0.0.1
Summary: Projeto DIO - processamento de imagens com Python
Home-page: https://github.com/glima-marcelo/Projetos_DIO/tree/master/Python/processamento-imagem-package
Author: Marcelo Goulart Lima
Author-email: glima.marcelo@gmail.com
License: UNKNOWN
Platform: UNKNOWN
Requires-Python: >=3.8
Requires-Dist: setuptools (==62.1.0)
Requires-Dist: scikit-image (~=0.19.2)
Requires-Dist: numpy (==1.22.3)
Requires-Dist: matplotlib (~=3.5.1)
